logot/__init__.py
logot/_asyncio.py
logot/_capture.py
logot/_import.py
logot/_level.py
logot/_logged.py
logot/_logging.py
logot/_logot.py
logot/_loguru.py
logot/_match.py
logot/_msg.py
logot/_name.py
logot/_pytest.py
logot/_structlog.py
logot/_trio.py
logot/_typing.py
logot/_unittest.py
logot/_validate.py
logot/_wait.py
logot/asyncio.py
logot/logged.py
logot/logging.py
logot/loguru.py
logot/py.typed
logot/structlog.py
logot/trio.py
logot/unittest.py
logot-1.5.1.dist-info/LICENSE
logot-1.5.1.dist-info/METADATA
logot-1.5.1.dist-info/WHEEL
logot-1.5.1.dist-info/entry_points.txt
logot-1.5.1.dist-info/RECORD
