Metadata-Version: 2.3
Name: logot
Version: 1.5.1
Summary: Test whether your code is logging correctly 🪵
License: MIT
Keywords: test,unittest,pytest,logging
Author: Dave Hall
Author-email: dave@etianen.com
Requires-Python: >=3.9,<4.0
Classifier: Development Status :: 5 - Production/Stable
Classifier: Framework :: AsyncIO
Classifier: Framework :: Pytest
Classifier: Framework :: Trio
Classifier: Intended Audience :: Developers
Classifier: License :: OSI Approved :: MIT License
Classifier: Programming Language :: Python :: 3
Classifier: Programming Language :: Python :: 3.9
Classifier: Programming Language :: Python :: 3.10
Classifier: Programming Language :: Python :: 3.11
Classifier: Programming Language :: Python :: 3.12
Classifier: Programming Language :: Python :: 3.13
Classifier: Topic :: Software Development :: Testing
Classifier: Topic :: Software Development :: Testing :: Unit
Classifier: Topic :: System :: Logging
Classifier: Typing :: Typed
Provides-Extra: loguru
Provides-Extra: pytest
Provides-Extra: structlog
Provides-Extra: trio
Requires-Dist: loguru ; extra == "loguru"
Requires-Dist: pytest ; extra == "pytest"
Requires-Dist: structlog ; extra == "structlog"
Requires-Dist: trio ; extra == "trio"
Requires-Dist: typing-extensions (>=4.9) ; python_version < "3.10"
Project-URL: Changelog, https://github.com/etianen/logot/releases
Project-URL: Documentation, https://logot.readthedocs.io
Project-URL: Homepage, https://logot.readthedocs.io
Project-URL: Repository, https://github.com/etianen/logot
Project-URL: Tracker, https://github.com/etianen/logot/issues
